gekko/__init__.py
gekko/gekko.py
theGekko-1.0.0.dist-info/DESCRIPTION.rst
theGekko-1.0.0.dist-info/METADATA
theGekko-1.0.0.dist-info/RECORD
theGekko-1.0.0.dist-info/WHEEL
theGekko-1.0.0.dist-info/entry_points.txt
theGekko-1.0.0.dist-info/metadata.json
theGekko-1.0.0.dist-info/top_level.txt
