Metadata-Version: 2.0
Name: theGekko
Version: 1.0.0
Summary: Make SFTP syncing "easy-peasy lizard squeezy".
Home-page: https://github.com/CYRO4S/Gekko
Author: Ralf Ren
Author-email: me@ralf.ren
License: UNKNOWN
Keywords: SFTP sftp sync
Platform: UNKNOWN
Classifier: Development Status :: 5 - Production/Stable
Classifier: Intended Audience :: Developers
Classifier: Intended Audience :: System Administrators
Classifier: Topic :: Software Development :: Build Tools
Classifier: Topic :: Communications :: File Sharing
Classifier: Topic :: System :: Networking
Classifier: License :: OSI Approved :: MIT License
Classifier: Programming Language :: Python :: 3
Classifier: Programming Language :: Python :: 3.4
Classifier: Programming Language :: Python :: 3.5
Classifier: Programming Language :: Python :: 3.6
Classifier: Environment :: Console
Classifier: Operating System :: POSIX :: Linux
Requires-Dist: PyYAML
Requires-Dist: pysftp
